ci_guardian/__init__.py
ci_guardian/cli.py
ci_guardian/core/__init__.py
ci_guardian/core/config.py
ci_guardian/core/installer.py
ci_guardian/core/venv_manager.py
ci_guardian/core/venv_validator.py
ci_guardian/hooks/__init__.py
ci_guardian/hooks/commit_msg.py
ci_guardian/hooks/post_commit.py
ci_guardian/hooks/pre_commit.py
ci_guardian/hooks/pre_push.py
ci_guardian/runners/__init__.py
ci_guardian/runners/github_actions.py
ci_guardian/validators/__init__.py
ci_guardian/validators/authorship.py
ci_guardian/validators/code_quality.py
ci_guardian/validators/common.py
ci_guardian/validators/file_utils.py
ci_guardian/validators/no_verify_blocker.py
ci_guardian/validators/security.py
ci_guardian-0.3.1.dist-info/licenses/AUTHORS.md
ci_guardian-0.3.1.dist-info/licenses/LICENSE
ci_guardian-0.3.1.dist-info/METADATA
ci_guardian-0.3.1.dist-info/WHEEL
ci_guardian-0.3.1.dist-info/entry_points.txt
ci_guardian-0.3.1.dist-info/top_level.txt
ci_guardian-0.3.1.dist-info/RECORD
