Metadata-Version: 2.4
Name: ci-guardian
Version: 0.3.1
Summary: Git hooks automation for Claude Code projects - enforces code quality, security, and prevents hook bypass
Author-email: Jarko <jarko@example.com>
License-Expression: MIT
Project-URL: Homepage, https://github.com/jarkillo/ci-guardian
Project-URL: Repository, https://github.com/jarkillo/ci-guardian
Project-URL: Issues, https://github.com/jarkillo/ci-guardian/issues
Project-URL: Documentation, https://github.com/jarkillo/ci-guardian#readme
Keywords: git-hooks,pre-commit,code-quality,security,claude-code,automation,linting,formatting,ci-cd
Classifier: Development Status :: 3 - Alpha
Classifier: Intended Audience :: Developers
Classifier: Programming Language :: Python :: 3
Classifier: Programming Language :: Python :: 3.10
Classifier: Programming Language :: Python :: 3.11
Classifier: Programming Language :: Python :: 3.12
Classifier: Programming Language :: Python :: 3.13
Classifier: Operating System :: OS Independent
Classifier: Operating System :: POSIX :: Linux
Classifier: Operating System :: Microsoft :: Windows
Classifier: Topic :: Software Development :: Quality Assurance
Classifier: Topic :: Software Development :: Version Control :: Git
Requires-Python: >=3.10
License-File: LICENSE
License-File: AUTHORS.md
Requires-Dist: click>=8.1.7
Requires-Dist: pyyaml>=6.0.2
Requires-Dist: colorama>=0.4.6
Requires-Dist: ruff>=0.8.0
Requires-Dist: black>=24.0.0
Requires-Dist: bandit[toml]>=1.8.0
Requires-Dist: safety>=3.0.0
Requires-Dist: tomli>=2.0.1; python_version < "3.11"
Provides-Extra: dev
Requires-Dist: pytest>=8.3.0; extra == "dev"
Requires-Dist: pytest-cov>=6.0.0; extra == "dev"
Requires-Dist: pytest-mock>=3.14.0; extra == "dev"
Requires-Dist: pytest-timeout>=2.3.0; extra == "dev"
Requires-Dist: mypy>=1.11.0; extra == "dev"
Provides-Extra: act
Requires-Dist: pyyaml>=6.0.2; extra == "act"
Dynamic: license-file
